meeting_guide/__init__.py
meeting_guide/admin.py
meeting_guide/apps.py
meeting_guide/models.py
meeting_guide/settings.py
meeting_guide/urls.py
meeting_guide/utils.py
meeting_guide/validators.py
meeting_guide/views.py
meeting_guide/wagtail_hooks.py
meeting_guide/fixtures/spec_meeting_types.json
meeting_guide/migrations/0001_initial.py
meeting_guide/migrations/0002_auto_20190907_0756.py
meeting_guide/migrations/0003_location_postal_code.py
meeting_guide/migrations/0004_auto_20200110_1611.py
meeting_guide/migrations/0005_auto_20200113_1831.py
meeting_guide/migrations/0006_auto_20200313_1850.py
meeting_guide/migrations/0007_auto_20200317_1933.py
meeting_guide/migrations/0008_auto_20200321_2037.py
meeting_guide/migrations/0009_auto_20200321_2220.py
meeting_guide/migrations/0010_auto_20200322_1025.py
meeting_guide/migrations/0011_auto_20200404_1829.py
meeting_guide/migrations/0012_auto_20200405_1015.py
meeting_guide/migrations/0013_auto_20200722_1634.py
meeting_guide/migrations/0014_auto_20200726_0929.py
meeting_guide/migrations/0015_auto_20211002_1711.py
meeting_guide/migrations/__init__.py
meeting_guide/static/meeting_guide/app.js
meeting_guide/static/meeting_guide/print.css
meeting_guide/templates/meeting_guide/location_form.html
meeting_guide/templates/meeting_guide/meetings_home.html
meeting_guide/templates/meeting_guide/tags/meeting_guide.html
meeting_guide/templates/wagtailadmin/pages/listing/_page_title_explore.html
meeting_guide/templates/wagtailadmin/pages/listing/_page_title_move.html
meeting_guide/templates/wagtailadmin/pages/listing/_page_title_move_AFTER_WAGTAIL_PR_IN_CODERED.html
meeting_guide/templatetags/__init__.py
meeting_guide/templatetags/meeting_guide.py
wagtail_meeting_guide-1.5.0.dist-info/LICENSE
wagtail_meeting_guide-1.5.0.dist-info/METADATA
wagtail_meeting_guide-1.5.0.dist-info/WHEEL
wagtail_meeting_guide-1.5.0.dist-info/top_level.txt
wagtail_meeting_guide-1.5.0.dist-info/RECORD
